jalali_calendar/__init__.py
jalali_calendar/__version__.py
jalali_calendar/converter.py
jalali_calendar/date.py
jalali_calendar/datetime.py
persian_jalali_calendar-1.1.0.dist-info/licenses/LICENSE
persian_jalali_calendar-1.1.0.dist-info/METADATA
persian_jalali_calendar-1.1.0.dist-info/WHEEL
persian_jalali_calendar-1.1.0.dist-info/top_level.txt
persian_jalali_calendar-1.1.0.dist-info/RECORD
