Metadata-Version: 2.4
Name: persian-jalali-calendar
Version: 1.1.0
Summary: A simple and accurate Python library for the Persian Jalali calendar.
Author-email: "Hamid R. Yari" <hryarih@gmail.com>
License: MIT License
Project-URL: Homepage, https://github.com/hryarih32/jalali-calendar
Project-URL: Bug Tracker, https://github.com/hryarih32/jalali-calendar/issues
Keywords: jalali,persian,calendar,shamsi,khorshidi,date,converter,datetime,timezone
Classifier: Development Status :: 5 - Production/Stable
Classifier: Intended Audience :: Developers
Classifier: Topic :: Software Development :: Libraries :: Python Modules
Classifier: Topic :: Utilities
Classifier: License :: OSI Approved :: MIT License
Classifier: Programming Language :: Python :: 3
Classifier: Programming Language :: Python :: 3.7
Classifier: Programming Language :: Python :: 3.8
Classifier: Programming Language :: Python :: 3.9
Classifier: Programming Language :: Python :: 3.10
Classifier: Programming Language :: Python :: 3.11
Classifier: Programming Language :: Python :: 3.12
Classifier: Operating System :: OS Independent
Requires-Python: >=3.7
License-File: LICENSE
Requires-Dist: backports.zoneinfo; python_version < "3.9"
Requires-Dist: tzdata
Dynamic: license-file
